functions_moedekjaer/__init__.py
modekjar/__init__.py
modekjar-0.0.3.dist-info/LICENSE
modekjar-0.0.3.dist-info/METADATA
modekjar-0.0.3.dist-info/WHEEL
modekjar-0.0.3.dist-info/top_level.txt
modekjar-0.0.3.dist-info/RECORD
